nselib/__init__.py
nselib/constants.py
nselib/libutil.py
nselib/logger.py
nselib/capital_market/__init__.py
nselib/capital_market/capital_market_data.py
nselib/capital_market/get_func.py
nselib/debt/__init__.py
nselib/debt/debt_data.py
nselib/derivatives/__init__.py
nselib/derivatives/derivative_data.py
nselib/derivatives/get_func.py
nselib/indices/__init__.py
nselib/indices/config.py
nselib/indices/index_data.py
nselib-2.4.1.dist-info/LICENSE
nselib-2.4.1.dist-info/METADATA
nselib-2.4.1.dist-info/WHEEL
nselib-2.4.1.dist-info/top_level.txt
nselib-2.4.1.dist-info/RECORD
