Metadata-Version: 2.1
Name: nselib
Version: 2.4.1
Summary: library to get NSE India data
Home-page: https://github.com/RuchiTanmay/nselib
Author: Ruchi Tanmay, Amlan Mishra
Author-email: ruchitanmay@gmail.com
License: UNKNOWN
Keywords: nseindia,nse,nse data,stock data,python,nse daily data,stock markets,nse library,nse python,nse daily reports
Platform: UNKNOWN
Classifier: Intended Audience :: Developers
Classifier: Natural Language :: English
Classifier: Operating System :: OS Independent
Classifier: Programming Language :: Python
Classifier: Programming Language :: Python :: 3
Classifier: Programming Language :: Python :: Implementation :: PyPy
Classifier: Topic :: Software Development :: Libraries :: Python Modules
License-File: LICENSE
Requires-Dist: requests
Requires-Dist: pandas
Requires-Dist: scipy
Requires-Dist: pandas-market-calendars
Requires-Dist: dateutil
